<annotation verified="yes">
	<folder>10葛中正</folder>
	<filename>L-GZZ-01.png</filename>
	<path>C:\Users\hehe\Desktop\朱予然图形\10葛中正\L-GZZ-01.png</path>
	<source>
		<database>Unknown</database>
	</source>
	<size>
		<width>1917</width>
		<height>1409</height>
		<depth>1</depth>
	</size>
	<segmented>0</segmented>
	<object>
		<name>goal</name>
		<pose>Unspecified</pose>
		<truncated>0</truncated>
		<difficult>0</difficult>
		<bndbox>
			<xmin>653</xmin>
			<ymin>51</ymin>
			<xmax>969</xmax>
			<ymax>225</ymax>
		</bndbox>
	</object>
	<object>
		<name>goal</name>
		<pose>Unspecified</pose>
		<truncated>0</truncated>
		<difficult>0</difficult>
		<bndbox>
			<xmin>375</xmin>
			<ymin>430</ymin>
			<xmax>757</xmax>
			<ymax>654</ymax>
		</bndbox>
	</object>
	<object>
		<name>goal</name>
		<pose>Unspecified</pose>
		<truncated>0</truncated>
		<difficult>0</difficult>
		<bndbox>
			<xmin>902</xmin>
			<ymin>425</ymin>
			<xmax>1284</xmax>
			<ymax>654</ymax>
		</bndbox>
	</object>
	<object>
		<name>task</name>
		<pose>Unspecified</pose>
		<truncated>0</truncated>
		<difficult>0</difficult>
		<bndbox>
			<xmin>36</xmin>
			<ymin>861</ymin>
			<xmax>453</xmax>
			<ymax>1094</ymax>
		</bndbox>
	</object>
	<object>
		<name>task</name>
		<pose>Unspecified</pose>
		<truncated>0</truncated>
		<difficult>0</difficult>
		<bndbox>
			<xmin>393</xmin>
			<ymin>1157</ymin>
			<xmax>768</xmax>
			<ymax>1340</ymax>
		</bndbox>
	</object>
	<object>
		<name>task</name>
		<pose>Unspecified</pose>
		<truncated>0</truncated>
		<difficult>0</difficult>
		<bndbox>
			<xmin>892</xmin>
			<ymin>1179</ymin>
			<xmax>1283</xmax>
			<ymax>1352</ymax>
		</bndbox>
	</object>
	<object>
		<name>task</name>
		<pose>Unspecified</pose>
		<truncated>0</truncated>
		<difficult>0</difficult>
		<bndbox>
			<xmin>1450</xmin>
			<ymin>1037</ymin>
			<xmax>1883</xmax>
			<ymax>1269</ymax>
		</bndbox>
	</object>
	<object>
		<name>and</name>
		<pose>Unspecified</pose>
		<truncated>0</truncated>
		<difficult>0</difficult>
		<bndbox>
			<xmin>677</xmin>
			<ymin>193</ymin>
			<xmax>748</xmax>
			<ymax>269</ymax>
		</bndbox>
	</object>
	<object>
		<name>and</name>
		<pose>Unspecified</pose>
		<truncated>0</truncated>
		<difficult>0</difficult>
		<bndbox>
			<xmin>910</xmin>
			<ymin>184</ymin>
			<xmax>992</xmax>
			<ymax>252</ymax>
		</bndbox>
	</object>
	<object>
		<name>arrow</name>
		<pose>Unspecified</pose>
		<truncated>0</truncated>
		<difficult>0</difficult>
		<bndbox>
			<xmin>387</xmin>
			<ymin>604</ymin>
			<xmax>459</xmax>
			<ymax>669</ymax>
		</bndbox>
	</object>
	<object>
		<name>arrow</name>
		<pose>Unspecified</pose>
		<truncated>0</truncated>
		<difficult>0</difficult>
		<bndbox>
			<xmin>611</xmin>
			<ymin>651</ymin>
			<xmax>674</xmax>
			<ymax>709</ymax>
		</bndbox>
	</object>
	<object>
		<name>arrow</name>
		<pose>Unspecified</pose>
		<truncated>0</truncated>
		<difficult>0</difficult>
		<bndbox>
			<xmin>1020</xmin>
			<ymin>649</ymin>
			<xmax>1087</xmax>
			<ymax>712</ymax>
		</bndbox>
	</object>
	<object>
		<name>arrow</name>
		<pose>Unspecified</pose>
		<truncated>0</truncated>
		<difficult>0</difficult>
		<bndbox>
			<xmin>1227</xmin>
			<ymin>612</ymin>
			<xmax>1311</xmax>
			<ymax>688</ymax>
		</bndbox>
	</object>
</annotation>
