<annotation verified="yes">
	<folder>29任宇鹏</folder>
	<filename>L-RYP-05.png</filename>
	<path>C:\Users\hehe\Desktop\朱予然图形34\29任宇鹏\L-RYP-05.png</path>
	<source>
		<database>Unknown</database>
	</source>
	<size>
		<width>3034</width>
		<height>3328</height>
		<depth>1</depth>
	</size>
	<segmented>0</segmented>
	<object>
		<name>task</name>
		<pose>Unspecified</pose>
		<truncated>0</truncated>
		<difficult>0</difficult>
		<bndbox>
			<xmin>986</xmin>
			<ymin>96</ymin>
			<xmax>2100</xmax>
			<ymax>921</ymax>
		</bndbox>
	</object>
	<object>
		<name>task</name>
		<pose>Unspecified</pose>
		<truncated>0</truncated>
		<difficult>0</difficult>
		<bndbox>
			<xmin>1954</xmin>
			<ymin>1621</ymin>
			<xmax>2972</xmax>
			<ymax>2417</ymax>
		</bndbox>
	</object>
	<object>
		<name>task</name>
		<pose>Unspecified</pose>
		<truncated>0</truncated>
		<difficult>0</difficult>
		<bndbox>
			<xmin>904</xmin>
			<ymin>2553</ymin>
			<xmax>2008</xmax>
			<ymax>3274</ymax>
		</bndbox>
	</object>
	<object>
		<name>goal</name>
		<pose>Unspecified</pose>
		<truncated>0</truncated>
		<difficult>0</difficult>
		<bndbox>
			<xmin>104</xmin>
			<ymin>1621</ymin>
			<xmax>943</xmax>
			<ymax>2421</ymax>
		</bndbox>
	</object>
	<object>
		<name>and</name>
		<pose>Unspecified</pose>
		<truncated>0</truncated>
		<difficult>0</difficult>
		<bndbox>
			<xmin>975</xmin>
			<ymin>763</ymin>
			<xmax>1218</xmax>
			<ymax>1056</ymax>
		</bndbox>
	</object>
	<object>
		<name>and</name>
		<pose>Unspecified</pose>
		<truncated>0</truncated>
		<difficult>0</difficult>
		<bndbox>
			<xmin>1443</xmin>
			<ymin>817</ymin>
			<xmax>1697</xmax>
			<ymax>1156</ymax>
		</bndbox>
	</object>
	<object>
		<name>and</name>
		<pose>Unspecified</pose>
		<truncated>0</truncated>
		<difficult>0</difficult>
		<bndbox>
			<xmin>1918</xmin>
			<ymin>660</ymin>
			<xmax>2254</xmax>
			<ymax>1092</ymax>
		</bndbox>
	</object>
</annotation>
