<annotation verified="yes">
	<folder>16王正</folder>
	<filename>L-WZ-06.png</filename>
	<path>C:\Users\hehe\Desktop\朱予然图形\16王正\L-WZ-06.png</path>
	<source>
		<database>Unknown</database>
	</source>
	<size>
		<width>2492</width>
		<height>1936</height>
		<depth>1</depth>
	</size>
	<segmented>0</segmented>
	<object>
		<name>quality</name>
		<pose>Unspecified</pose>
		<truncated>0</truncated>
		<difficult>0</difficult>
		<bndbox>
			<xmin>712</xmin>
			<ymin>87</ymin>
			<xmax>1390</xmax>
			<ymax>418</ymax>
		</bndbox>
	</object>
	<object>
		<name>quality</name>
		<pose>Unspecified</pose>
		<truncated>0</truncated>
		<difficult>0</difficult>
		<bndbox>
			<xmin>1840</xmin>
			<ymin>758</ymin>
			<xmax>2400</xmax>
			<ymax>1068</ymax>
		</bndbox>
	</object>
	<object>
		<name>task</name>
		<pose>Unspecified</pose>
		<truncated>0</truncated>
		<difficult>0</difficult>
		<bndbox>
			<xmin>269</xmin>
			<ymin>761</ymin>
			<xmax>769</xmax>
			<ymax>1120</ymax>
		</bndbox>
	</object>
	<object>
		<name>task</name>
		<pose>Unspecified</pose>
		<truncated>0</truncated>
		<difficult>0</difficult>
		<bndbox>
			<xmin>55</xmin>
			<ymin>1508</ymin>
			<xmax>509</xmax>
			<ymax>1861</ymax>
		</bndbox>
	</object>
	<object>
		<name>task</name>
		<pose>Unspecified</pose>
		<truncated>0</truncated>
		<difficult>0</difficult>
		<bndbox>
			<xmin>690</xmin>
			<ymin>1444</ymin>
			<xmax>1121</xmax>
			<ymax>1818</ymax>
		</bndbox>
	</object>
	<object>
		<name>or</name>
		<pose>Unspecified</pose>
		<truncated>0</truncated>
		<difficult>0</difficult>
		<bndbox>
			<xmin>752</xmin>
			<ymin>370</ymin>
			<xmax>871</xmax>
			<ymax>515</ymax>
		</bndbox>
	</object>
	<object>
		<name>or</name>
		<pose>Unspecified</pose>
		<truncated>0</truncated>
		<difficult>0</difficult>
		<bndbox>
			<xmin>1059</xmin>
			<ymin>363</ymin>
			<xmax>1207</xmax>
			<ymax>496</ymax>
		</bndbox>
	</object>
	<object>
		<name>or</name>
		<pose>Unspecified</pose>
		<truncated>0</truncated>
		<difficult>0</difficult>
		<bndbox>
			<xmin>1333</xmin>
			<ymin>332</ymin>
			<xmax>1466</xmax>
			<ymax>453</ymax>
		</bndbox>
	</object>
	<object>
		<name>and</name>
		<pose>Unspecified</pose>
		<truncated>0</truncated>
		<difficult>0</difficult>
		<bndbox>
			<xmin>386</xmin>
			<ymin>1082</ymin>
			<xmax>495</xmax>
			<ymax>1211</ymax>
		</bndbox>
	</object>
	<object>
		<name>and</name>
		<pose>Unspecified</pose>
		<truncated>0</truncated>
		<difficult>0</difficult>
		<bndbox>
			<xmin>609</xmin>
			<ymin>1072</ymin>
			<xmax>821</xmax>
			<ymax>1253</ymax>
		</bndbox>
	</object>
	<object>
		<name>goal</name>
		<pose>Unspecified</pose>
		<truncated>0</truncated>
		<difficult>0</difficult>
		<bndbox>
			<xmin>986</xmin>
			<ymin>746</ymin>
			<xmax>1505</xmax>
			<ymax>1139</ymax>
		</bndbox>
	</object>
</annotation>
