<annotation verified="yes">
	<folder>15夏天麒</folder>
	<filename>L-XTQ-10.png</filename>
	<path>C:\Users\hehe\Desktop\朱予然图形\15夏天麒\L-XTQ-10.png</path>
	<source>
		<database>Unknown</database>
	</source>
	<size>
		<width>3098</width>
		<height>2208</height>
		<depth>1</depth>
	</size>
	<segmented>0</segmented>
	<object>
		<name>role</name>
		<pose>Unspecified</pose>
		<truncated>0</truncated>
		<difficult>0</difficult>
		<bndbox>
			<xmin>93</xmin>
			<ymin>553</ymin>
			<xmax>457</xmax>
			<ymax>974</ymax>
		</bndbox>
	</object>
	<object>
		<name>resource</name>
		<pose>Unspecified</pose>
		<truncated>0</truncated>
		<difficult>0</difficult>
		<bndbox>
			<xmin>840</xmin>
			<ymin>59</ymin>
			<xmax>1390</xmax>
			<ymax>374</ymax>
		</bndbox>
	</object>
	<object>
		<name>goal</name>
		<pose>Unspecified</pose>
		<truncated>0</truncated>
		<difficult>0</difficult>
		<bndbox>
			<xmin>540</xmin>
			<ymin>903</ymin>
			<xmax>1140</xmax>
			<ymax>1195</ymax>
		</bndbox>
	</object>
	<object>
		<name>task</name>
		<pose>Unspecified</pose>
		<truncated>0</truncated>
		<difficult>0</difficult>
		<bndbox>
			<xmin>216</xmin>
			<ymin>1630</ymin>
			<xmax>869</xmax>
			<ymax>2000</ymax>
		</bndbox>
	</object>
	<object>
		<name>actor</name>
		<pose>Unspecified</pose>
		<truncated>0</truncated>
		<difficult>0</difficult>
		<bndbox>
			<xmin>2022</xmin>
			<ymin>1633</ymin>
			<xmax>2460</xmax>
			<ymax>2124</ymax>
		</bndbox>
	</object>
	<object>
		<name>agent</name>
		<pose>Unspecified</pose>
		<truncated>0</truncated>
		<difficult>0</difficult>
		<bndbox>
			<xmin>1566</xmin>
			<ymin>712</ymin>
			<xmax>1940</xmax>
			<ymax>1127</ymax>
		</bndbox>
	</object>
	<object>
		<name>quality</name>
		<pose>Unspecified</pose>
		<truncated>0</truncated>
		<difficult>0</difficult>
		<bndbox>
			<xmin>2313</xmin>
			<ymin>950</ymin>
			<xmax>2975</xmax>
			<ymax>1256</ymax>
		</bndbox>
	</object>
	<object>
		<name>arrow</name>
		<pose>Unspecified</pose>
		<truncated>0</truncated>
		<difficult>0</difficult>
		<bndbox>
			<xmin>752</xmin>
			<ymin>174</ymin>
			<xmax>866</xmax>
			<ymax>345</ymax>
		</bndbox>
	</object>
	<object>
		<name>arrow</name>
		<pose>Unspecified</pose>
		<truncated>0</truncated>
		<difficult>0</difficult>
		<bndbox>
			<xmin>1010</xmin>
			<ymin>333</ymin>
			<xmax>1151</xmax>
			<ymax>450</ymax>
		</bndbox>
	</object>
	<object>
		<name>arrow</name>
		<pose>Unspecified</pose>
		<truncated>0</truncated>
		<difficult>0</difficult>
		<bndbox>
			<xmin>1196</xmin>
			<ymin>324</ymin>
			<xmax>1328</xmax>
			<ymax>465</ymax>
		</bndbox>
	</object>
	<object>
		<name>arrow</name>
		<pose>Unspecified</pose>
		<truncated>0</truncated>
		<difficult>0</difficult>
		<bndbox>
			<xmin>1905</xmin>
			<ymin>845</ymin>
			<xmax>2005</xmax>
			<ymax>956</ymax>
		</bndbox>
	</object>
	<object>
		<name>arrow</name>
		<pose>Unspecified</pose>
		<truncated>0</truncated>
		<difficult>0</difficult>
		<bndbox>
			<xmin>1760</xmin>
			<ymin>1098</ymin>
			<xmax>1899</xmax>
			<ymax>1239</ymax>
		</bndbox>
	</object>
</annotation>
