<annotation verified="yes">
	<folder>19张瑞阳</folder>
	<filename>L-ZRY-17.png</filename>
	<path>C:\Users\hehe\Desktop\朱予然图形34\19张瑞阳\L-ZRY-17.png</path>
	<source>
		<database>Unknown</database>
	</source>
	<size>
		<width>2508</width>
		<height>1712</height>
		<depth>1</depth>
	</size>
	<segmented>0</segmented>
	<object>
		<name>task</name>
		<pose>Unspecified</pose>
		<truncated>0</truncated>
		<difficult>0</difficult>
		<bndbox>
			<xmin>83</xmin>
			<ymin>1254</ymin>
			<xmax>562</xmax>
			<ymax>1639</ymax>
		</bndbox>
	</object>
	<object>
		<name>task</name>
		<pose>Unspecified</pose>
		<truncated>0</truncated>
		<difficult>0</difficult>
		<bndbox>
			<xmin>720</xmin>
			<ymin>1254</ymin>
			<xmax>1249</xmax>
			<ymax>1615</ymax>
		</bndbox>
	</object>
	<object>
		<name>task</name>
		<pose>Unspecified</pose>
		<truncated>0</truncated>
		<difficult>0</difficult>
		<bndbox>
			<xmin>836</xmin>
			<ymin>59</ymin>
			<xmax>1347</xmax>
			<ymax>439</ymax>
		</bndbox>
	</object>
	<object>
		<name>quality</name>
		<pose>Unspecified</pose>
		<truncated>0</truncated>
		<difficult>0</difficult>
		<bndbox>
			<xmin>358</xmin>
			<ymin>685</ymin>
			<xmax>907</xmax>
			<ymax>969</ymax>
		</bndbox>
	</object>
	<object>
		<name>quality</name>
		<pose>Unspecified</pose>
		<truncated>0</truncated>
		<difficult>0</difficult>
		<bndbox>
			<xmin>1321</xmin>
			<ymin>1300</ymin>
			<xmax>1805</xmax>
			<ymax>1624</ymax>
		</bndbox>
	</object>
	<object>
		<name>quality</name>
		<pose>Unspecified</pose>
		<truncated>0</truncated>
		<difficult>0</difficult>
		<bndbox>
			<xmin>1832</xmin>
			<ymin>1282</ymin>
			<xmax>2419</xmax>
			<ymax>1604</ymax>
		</bndbox>
	</object>
	<object>
		<name>goal</name>
		<pose>Unspecified</pose>
		<truncated>0</truncated>
		<difficult>0</difficult>
		<bndbox>
			<xmin>1508</xmin>
			<ymin>730</ymin>
			<xmax>2001</xmax>
			<ymax>1065</ymax>
		</bndbox>
	</object>
	<object>
		<name>and</name>
		<pose>Unspecified</pose>
		<truncated>0</truncated>
		<difficult>0</difficult>
		<bndbox>
			<xmin>838</xmin>
			<ymin>406</ymin>
			<xmax>951</xmax>
			<ymax>500</ymax>
		</bndbox>
	</object>
	<object>
		<name>and</name>
		<pose>Unspecified</pose>
		<truncated>0</truncated>
		<difficult>0</difficult>
		<bndbox>
			<xmin>1214</xmin>
			<ymin>417</ymin>
			<xmax>1316</xmax>
			<ymax>513</ymax>
		</bndbox>
	</object>
	<object>
		<name>or</name>
		<pose>Unspecified</pose>
		<truncated>0</truncated>
		<difficult>0</difficult>
		<bndbox>
			<xmin>336</xmin>
			<ymin>941</ymin>
			<xmax>507</xmax>
			<ymax>1061</ymax>
		</bndbox>
	</object>
	<object>
		<name>or</name>
		<pose>Unspecified</pose>
		<truncated>0</truncated>
		<difficult>0</difficult>
		<bndbox>
			<xmin>766</xmin>
			<ymin>919</ymin>
			<xmax>925</xmax>
			<ymax>1048</ymax>
		</bndbox>
	</object>
	<object>
		<name>or</name>
		<pose>Unspecified</pose>
		<truncated>0</truncated>
		<difficult>0</difficult>
		<bndbox>
			<xmin>1562</xmin>
			<ymin>1011</ymin>
			<xmax>1712</xmax>
			<ymax>1130</ymax>
		</bndbox>
	</object>
	<object>
		<name>or</name>
		<pose>Unspecified</pose>
		<truncated>0</truncated>
		<difficult>0</difficult>
		<bndbox>
			<xmin>1873</xmin>
			<ymin>1004</ymin>
			<xmax>2033</xmax>
			<ymax>1126</ymax>
		</bndbox>
	</object>
</annotation>
