<annotation verified="yes">
	<folder>02朱一力</folder>
	<filename>L-ZYL-05.png</filename>
	<path>C:\Users\hehe\Desktop\朱予然图形\02朱一力\L-ZYL-05.png</path>
	<source>
		<database>Unknown</database>
	</source>
	<size>
		<width>2380</width>
		<height>1536</height>
		<depth>1</depth>
	</size>
	<segmented>0</segmented>
	<object>
		<name>task</name>
		<pose>Unspecified</pose>
		<truncated>0</truncated>
		<difficult>0</difficult>
		<bndbox>
			<xmin>868</xmin>
			<ymin>104</ymin>
			<xmax>1485</xmax>
			<ymax>465</ymax>
		</bndbox>
	</object>
	<object>
		<name>task</name>
		<pose>Unspecified</pose>
		<truncated>0</truncated>
		<difficult>0</difficult>
		<bndbox>
			<xmin>796</xmin>
			<ymin>1078</ymin>
			<xmax>1408</xmax>
			<ymax>1435</ymax>
		</bndbox>
	</object>
	<object>
		<name>task</name>
		<pose>Unspecified</pose>
		<truncated>0</truncated>
		<difficult>0</difficult>
		<bndbox>
			<xmin>1645</xmin>
			<ymin>846</ymin>
			<xmax>2287</xmax>
			<ymax>1176</ymax>
		</bndbox>
	</object>
	<object>
		<name>goal</name>
		<pose>Unspecified</pose>
		<truncated>0</truncated>
		<difficult>0</difficult>
		<bndbox>
			<xmin>96</xmin>
			<ymin>728</ymin>
			<xmax>659</xmax>
			<ymax>1006</ymax>
		</bndbox>
	</object>
	<object>
		<name>and</name>
		<pose>Unspecified</pose>
		<truncated>0</truncated>
		<difficult>0</difficult>
		<bndbox>
			<xmin>815</xmin>
			<ymin>350</ymin>
			<xmax>973</xmax>
			<ymax>516</ymax>
		</bndbox>
	</object>
	<object>
		<name>and</name>
		<pose>Unspecified</pose>
		<truncated>0</truncated>
		<difficult>0</difficult>
		<bndbox>
			<xmin>1119</xmin>
			<ymin>425</ymin>
			<xmax>1268</xmax>
			<ymax>525</ymax>
		</bndbox>
	</object>
	<object>
		<name>and</name>
		<pose>Unspecified</pose>
		<truncated>0</truncated>
		<difficult>0</difficult>
		<bndbox>
			<xmin>1369</xmin>
			<ymin>346</ymin>
			<xmax>1506</xmax>
			<ymax>483</ymax>
		</bndbox>
	</object>
</annotation>
