<annotation verified="yes">
	<folder>01朱予然</folder>
	<filename>L-ZYR-17.png</filename>
	<path>C:\Users\hehe\Desktop\朱予然图形\01朱予然\L-ZYR-17.png</path>
	<source>
		<database>Unknown</database>
	</source>
	<size>
		<width>3082</width>
		<height>1856</height>
		<depth>1</depth>
	</size>
	<segmented>0</segmented>
	<object>
		<name>task</name>
		<pose>Unspecified</pose>
		<truncated>0</truncated>
		<difficult>0</difficult>
		<bndbox>
			<xmin>1046</xmin>
			<ymin>89</ymin>
			<xmax>1673</xmax>
			<ymax>455</ymax>
		</bndbox>
	</object>
	<object>
		<name>task</name>
		<pose>Unspecified</pose>
		<truncated>0</truncated>
		<difficult>0</difficult>
		<bndbox>
			<xmin>125</xmin>
			<ymin>1391</ymin>
			<xmax>714</xmax>
			<ymax>1734</ymax>
		</bndbox>
	</object>
	<object>
		<name>task</name>
		<pose>Unspecified</pose>
		<truncated>0</truncated>
		<difficult>0</difficult>
		<bndbox>
			<xmin>939</xmin>
			<ymin>1394</ymin>
			<xmax>1441</xmax>
			<ymax>1730</ymax>
		</bndbox>
	</object>
	<object>
		<name>quality</name>
		<pose>Unspecified</pose>
		<truncated>0</truncated>
		<difficult>0</difficult>
		<bndbox>
			<xmin>528</xmin>
			<ymin>696</ymin>
			<xmax>1137</xmax>
			<ymax>1094</ymax>
		</bndbox>
	</object>
	<object>
		<name>quality</name>
		<pose>Unspecified</pose>
		<truncated>0</truncated>
		<difficult>0</difficult>
		<bndbox>
			<xmin>1607</xmin>
			<ymin>1416</ymin>
			<xmax>2164</xmax>
			<ymax>1757</ymax>
		</bndbox>
	</object>
	<object>
		<name>quality</name>
		<pose>Unspecified</pose>
		<truncated>0</truncated>
		<difficult>0</difficult>
		<bndbox>
			<xmin>2328</xmin>
			<ymin>1478</ymin>
			<xmax>2950</xmax>
			<ymax>1812</ymax>
		</bndbox>
	</object>
	<object>
		<name>goal</name>
		<pose>Unspecified</pose>
		<truncated>0</truncated>
		<difficult>0</difficult>
		<bndbox>
			<xmin>1866</xmin>
			<ymin>821</ymin>
			<xmax>2514</xmax>
			<ymax>1155</ymax>
		</bndbox>
	</object>
	<object>
		<name>and</name>
		<pose>Unspecified</pose>
		<truncated>0</truncated>
		<difficult>0</difficult>
		<bndbox>
			<xmin>1134</xmin>
			<ymin>382</ymin>
			<xmax>1230</xmax>
			<ymax>514</ymax>
		</bndbox>
	</object>
	<object>
		<name>and</name>
		<pose>Unspecified</pose>
		<truncated>0</truncated>
		<difficult>0</difficult>
		<bndbox>
			<xmin>1528</xmin>
			<ymin>339</ymin>
			<xmax>1648</xmax>
			<ymax>457</ymax>
		</bndbox>
	</object>
	<object>
		<name>or</name>
		<pose>Unspecified</pose>
		<truncated>0</truncated>
		<difficult>0</difficult>
		<bndbox>
			<xmin>523</xmin>
			<ymin>1034</ymin>
			<xmax>671</xmax>
			<ymax>1173</ymax>
		</bndbox>
	</object>
	<object>
		<name>or</name>
		<pose>Unspecified</pose>
		<truncated>0</truncated>
		<difficult>0</difficult>
		<bndbox>
			<xmin>973</xmin>
			<ymin>1007</ymin>
			<xmax>1103</xmax>
			<ymax>1139</ymax>
		</bndbox>
	</object>
	<object>
		<name>or</name>
		<pose>Unspecified</pose>
		<truncated>0</truncated>
		<difficult>0</difficult>
		<bndbox>
			<xmin>1984</xmin>
			<ymin>1071</ymin>
			<xmax>2103</xmax>
			<ymax>1194</ymax>
		</bndbox>
	</object>
	<object>
		<name>or</name>
		<pose>Unspecified</pose>
		<truncated>0</truncated>
		<difficult>0</difficult>
		<bndbox>
			<xmin>2353</xmin>
			<ymin>1084</ymin>
			<xmax>2512</xmax>
			<ymax>1216</ymax>
		</bndbox>
	</object>
</annotation>
