<annotation verified="yes">
	<folder>09赵子钰</folder>
	<filename>L-ZZY-15.png</filename>
	<path>C:\Users\hehe\Desktop\朱予然图形\09赵子钰\L-ZZY-15.png</path>
	<source>
		<database>Unknown</database>
	</source>
	<size>
		<width>1701</width>
		<height>1397</height>
		<depth>1</depth>
	</size>
	<segmented>0</segmented>
	<object>
		<name>quality</name>
		<pose>Unspecified</pose>
		<truncated>0</truncated>
		<difficult>0</difficult>
		<bndbox>
			<xmin>630</xmin>
			<ymin>51</ymin>
			<xmax>1093</xmax>
			<ymax>307</ymax>
		</bndbox>
	</object>
	<object>
		<name>actor</name>
		<pose>Unspecified</pose>
		<truncated>0</truncated>
		<difficult>0</difficult>
		<bndbox>
			<xmin>100</xmin>
			<ymin>630</ymin>
			<xmax>342</xmax>
			<ymax>873</ymax>
		</bndbox>
	</object>
	<object>
		<name>role</name>
		<pose>Unspecified</pose>
		<truncated>0</truncated>
		<difficult>0</difficult>
		<bndbox>
			<xmin>714</xmin>
			<ymin>545</ymin>
			<xmax>978</xmax>
			<ymax>791</ymax>
		</bndbox>
	</object>
	<object>
		<name>agent</name>
		<pose>Unspecified</pose>
		<truncated>0</truncated>
		<difficult>0</difficult>
		<bndbox>
			<xmin>1349</xmin>
			<ymin>573</ymin>
			<xmax>1599</xmax>
			<ymax>839</ymax>
		</bndbox>
	</object>
	<object>
		<name>resource</name>
		<pose>Unspecified</pose>
		<truncated>0</truncated>
		<difficult>0</difficult>
		<bndbox>
			<xmin>63</xmin>
			<ymin>1157</ymin>
			<xmax>333</xmax>
			<ymax>1360</ymax>
		</bndbox>
	</object>
	<object>
		<name>goal</name>
		<pose>Unspecified</pose>
		<truncated>0</truncated>
		<difficult>0</difficult>
		<bndbox>
			<xmin>670</xmin>
			<ymin>1122</ymin>
			<xmax>976</xmax>
			<ymax>1355</ymax>
		</bndbox>
	</object>
	<object>
		<name>task</name>
		<pose>Unspecified</pose>
		<truncated>0</truncated>
		<difficult>0</difficult>
		<bndbox>
			<xmin>1352</xmin>
			<ymin>1063</ymin>
			<xmax>1643</xmax>
			<ymax>1270</ymax>
		</bndbox>
	</object>
	<object>
		<name>arrow</name>
		<pose>Unspecified</pose>
		<truncated>0</truncated>
		<difficult>0</difficult>
		<bndbox>
			<xmin>652</xmin>
			<ymin>273</ymin>
			<xmax>717</xmax>
			<ymax>366</ymax>
		</bndbox>
	</object>
	<object>
		<name>arrow</name>
		<pose>Unspecified</pose>
		<truncated>0</truncated>
		<difficult>0</difficult>
		<bndbox>
			<xmin>822</xmin>
			<ymin>239</ymin>
			<xmax>897</xmax>
			<ymax>303</ymax>
		</bndbox>
	</object>
	<object>
		<name>arrow</name>
		<pose>Unspecified</pose>
		<truncated>0</truncated>
		<difficult>0</difficult>
		<bndbox>
			<xmin>1002</xmin>
			<ymin>228</ymin>
			<xmax>1087</xmax>
			<ymax>300</ymax>
		</bndbox>
	</object>
	<object>
		<name>arrow</name>
		<pose>Unspecified</pose>
		<truncated>0</truncated>
		<difficult>0</difficult>
		<bndbox>
			<xmin>178</xmin>
			<ymin>846</ymin>
			<xmax>257</xmax>
			<ymax>910</ymax>
		</bndbox>
	</object>
	<object>
		<name>arrow</name>
		<pose>Unspecified</pose>
		<truncated>0</truncated>
		<difficult>0</difficult>
		<bndbox>
			<xmin>797</xmin>
			<ymin>767</ymin>
			<xmax>882</xmax>
			<ymax>830</ymax>
		</bndbox>
	</object>
	<object>
		<name>arrow</name>
		<pose>Unspecified</pose>
		<truncated>0</truncated>
		<difficult>0</difficult>
		<bndbox>
			<xmin>1446</xmin>
			<ymin>809</ymin>
			<xmax>1537</xmax>
			<ymax>879</ymax>
		</bndbox>
	</object>
</annotation>
